opensubmit_exec-0.7.17.dist-info/METADATA
opensubmit_exec-0.7.17.dist-info/RECORD
opensubmit_exec-0.7.17.dist-info/WHEEL
opensubmit_exec-0.7.17.dist-info/entry_points.txt
opensubmit_exec-0.7.17.dist-info/top_level.txt
opensubmitexec/__init__.py
opensubmitexec/cmdline.py
opensubmitexec/compiler.py
opensubmitexec/config.py
opensubmitexec/exceptions.py
opensubmitexec/filesystem.py
opensubmitexec/helpers.py
opensubmitexec/hostinfo.py
opensubmitexec/internaljob.py
opensubmitexec/job.py
opensubmitexec/locking.py
opensubmitexec/running.py
opensubmitexec/server.py
