Metadata-Version: 2.1
Name: opensubmit-exec
Version: 0.7.17
Summary: This is the executor daemon for the OpenSubmit web application.
Home-page: https://github.com/troeger/opensubmit
Author: Peter Tröger
Author-email: peter@troeger.eu
License: AGPL
Platform: UNKNOWN
Classifier: Development Status :: 4 - Beta
Classifier: Programming Language :: Python :: 3.6
Classifier: Programming Language :: Python :: 3.5
Classifier: Programming Language :: Python :: 3.4
Provides-Extra: report-opencl
Requires-Dist: psutil
Requires-Dist: twisted
Requires-Dist: py-cpuinfo
Requires-Dist: pexpect
Provides-Extra: report-opencl
Requires-Dist: pyopencl; extra == 'report-opencl'
